kafka_python_app/__init__.py
kafka_python_app/app.py
kafka_python_app/connector.py
kafka_python_app-0.3.7.dist-info/licenses/LICENSE.md
kafka_python_app-0.3.7.dist-info/METADATA
kafka_python_app-0.3.7.dist-info/WHEEL
kafka_python_app-0.3.7.dist-info/top_level.txt
kafka_python_app-0.3.7.dist-info/RECORD
