Metadata-Version: 2.4
Name: kafka_python_app
Version: 0.3.7
Summary: kafka application endpoint
Home-page: https://github.com/doctor3030/kafka-python-app.git
Author: Dmitry Amanov
Author-email: dmitry.amanov@gmail.com
License: MIT
Classifier: License :: OSI Approved :: MIT License
Classifier: Programming Language :: Python :: 3
Requires-Python: >=3.8
License-File: LICENSE.md
Requires-Dist: pydantic~=2.11.0
Requires-Dist: kafka-python~=2.0.6
Dynamic: author
Dynamic: author-email
Dynamic: classifier
Dynamic: description
Dynamic: description-content-type
Dynamic: home-page
Dynamic: license
Dynamic: license-file
Dynamic: requires-dist
Dynamic: requires-python
Dynamic: summary
